[
    {
        "commit_sha": "f8cb312032d413f00f517f73f662edb0bf16c16c",
        "issues": {
            "issues": [
                {
                    "key": "AY5SlF0EAESW5py-ls0_",
                    "rule": "java:S112",
                    "severity": "MAJOR",
                    "component": "accumulo-4029:test/src/main/java/org/apache/accumulo/test/fate/zookeeper/FateIT.java",
                    "status": "OPEN",
                    "debt": "20min",
                    "type": "CODE_SMELL",
                    "textRange": {
                        "startLine": 131,
                        "endLine": 131,
                        "startOffset": 36,
                        "endOffset": 45
                    }
                },
                {
                    "key": "AY5SlF0EAESW5py-ls1A",
                    "rule": "java:S112",
                    "severity": "MAJOR",
                    "component": "accumulo-4029:test/src/main/java/org/apache/accumulo/test/fate/zookeeper/FateIT.java",
                    "status": "OPEN",
                    "debt": "20min",
                    "type": "CODE_SMELL",
                    "textRange": {
                        "startLine": 142,
                        "endLine": 142,
                        "startOffset": 39,
                        "endOffset": 48
                    }
                },
                {
                    "key": "AY5SlF0EAESW5py-ls1B",
                    "rule": "java:S2293",
                    "severity": "MINOR",
                    "component": "accumulo-4029:test/src/main/java/org/apache/accumulo/test/fate/zookeeper/FateIT.java",
                    "status": "OPEN",
                    "debt": "1min",
                    "type": "CODE_SMELL",
                    "textRange": {
                        "startLine": 150,
                        "endLine": 150,
                        "startOffset": 51,
                        "endOffset": 60
                    }
                },
                {
                    "key": "AY5SlF0EAESW5py-ls1C",
                    "rule": "java:S2293",
                    "severity": "MINOR",
                    "component": "accumulo-4029:test/src/main/java/org/apache/accumulo/test/fate/zookeeper/FateIT.java",
                    "status": "OPEN",
                    "debt": "1min",
                    "type": "CODE_SMELL",
                    "textRange": {
                        "startLine": 152,
                        "endLine": 152,
                        "startOffset": 23,
                        "endOffset": 32
                    }
                },
                {
                    "key": "AY5SlF0EAESW5py-ls1D",
                    "rule": "java:S2293",
                    "severity": "MINOR",
                    "component": "accumulo-4029:test/src/main/java/org/apache/accumulo/test/fate/zookeeper/FateIT.java",
                    "status": "OPEN",
                    "debt": "1min",
                    "type": "CODE_SMELL",
                    "textRange": {
                        "startLine": 161,
                        "endLine": 161,
                        "startOffset": 33,
                        "endOffset": 42
                    }
                },
                {
                    "key": "AY5SlF0EAESW5py-ls1U",
                    "rule": "java:S2696",
                    "severity": "CRITICAL",
                    "component": "accumulo-4029:test/src/main/java/org/apache/accumulo/test/fate/zookeeper/FateIT.java",
                    "status": "OPEN",
                    "debt": "20min",
                    "type": "CODE_SMELL",
                    "textRange": {
                        "startLine": 171,
                        "endLine": 171,
                        "startOffset": 6,
                        "endOffset": 17
                    }
                },
                {
                    "key": "AY5SlF0EAESW5py-ls1V",
                    "rule": "java:S2696",
                    "severity": "CRITICAL",
                    "component": "accumulo-4029:test/src/main/java/org/apache/accumulo/test/fate/zookeeper/FateIT.java",
                    "status": "OPEN",
                    "debt": "20min",
                    "type": "CODE_SMELL",
                    "textRange": {
                        "startLine": 172,
                        "endLine": 172,
                        "startOffset": 6,
                        "endOffset": 16
                    }
                },
                {
                    "key": "AY5SlF0EAESW5py-ls1Q",
                    "rule": "java:S1192",
                    "severity": "CRITICAL",
                    "component": "accumulo-4029:test/src/main/java/org/apache/accumulo/test/fate/zookeeper/FateIT.java",
                    "status": "OPEN",
                    "debt": "12min",
                    "type": "CODE_SMELL",
                    "textRange": {
                        "startLine": 176,
                        "endLine": 176,
                        "startOffset": 84,
                        "endOffset": 93
                    }
                },
                {
                    "key": "AY5SlF0EAESW5py-ls1R",
                    "rule": "java:S1192",
                    "severity": "CRITICAL",
                    "component": "accumulo-4029:test/src/main/java/org/apache/accumulo/test/fate/zookeeper/FateIT.java",
                    "status": "OPEN",
                    "debt": "12min",
                    "type": "CODE_SMELL",
                    "textRange": {
                        "startLine": 176,
                        "endLine": 176,
                        "startOffset": 27,
                        "endOffset": 42
                    }
                },
                {
                    "key": "AY5SlF0EAESW5py-ls1S",
                    "rule": "java:S2189",
                    "severity": "BLOCKER",
                    "component": "accumulo-4029:test/src/main/java/org/apache/accumulo/test/fate/zookeeper/FateIT.java",
                    "status": "OPEN",
                    "debt": "15min",
                    "type": "BUG",
                    "textRange": {
                        "startLine": 191,
                        "endLine": 202,
                        "startOffset": 6,
                        "endOffset": 7
                    }
                },
                {
                    "key": "AY5SlF0EAESW5py-ls1T",
                    "rule": "java:S2589",
                    "severity": "MAJOR",
                    "component": "accumulo-4029:test/src/main/java/org/apache/accumulo/test/fate/zookeeper/FateIT.java",
                    "status": "OPEN",
                    "debt": "10min",
                    "type": "CODE_SMELL",
                    "textRange": {
                        "startLine": 191,
                        "endLine": 191,
                        "startOffset": 13,
                        "endOffset": 23
                    }
                },
                {
                    "key": "AY5SlF0EAESW5py-ls1E",
                    "rule": "java:S2293",
                    "severity": "MINOR",
                    "component": "accumulo-4029:test/src/main/java/org/apache/accumulo/test/fate/zookeeper/FateIT.java",
                    "status": "OPEN",
                    "debt": "1min",
                    "type": "CODE_SMELL",
                    "textRange": {
                        "startLine": 211,
                        "endLine": 211,
                        "startOffset": 51,
                        "endOffset": 60
                    }
                },
                {
                    "key": "AY5SlF0EAESW5py-ls1F",
                    "rule": "java:S2293",
                    "severity": "MINOR",
                    "component": "accumulo-4029:test/src/main/java/org/apache/accumulo/test/fate/zookeeper/FateIT.java",
                    "status": "OPEN",
                    "debt": "1min",
                    "type": "CODE_SMELL",
                    "textRange": {
                        "startLine": 213,
                        "endLine": 213,
                        "startOffset": 23,
                        "endOffset": 32
                    }
                },
                {
                    "key": "AY5SlF0EAESW5py-ls1G",
                    "rule": "java:S2293",
                    "severity": "MINOR",
                    "component": "accumulo-4029:test/src/main/java/org/apache/accumulo/test/fate/zookeeper/FateIT.java",
                    "status": "OPEN",
                    "debt": "1min",
                    "type": "CODE_SMELL",
                    "textRange": {
                        "startLine": 222,
                        "endLine": 222,
                        "startOffset": 33,
                        "endOffset": 42
                    }
                },
                {
                    "key": "AY5SlF0EAESW5py-ls1W",
                    "rule": "java:S2696",
                    "severity": "CRITICAL",
                    "component": "accumulo-4029:test/src/main/java/org/apache/accumulo/test/fate/zookeeper/FateIT.java",
                    "status": "OPEN",
                    "debt": "20min",
                    "type": "CODE_SMELL",
                    "textRange": {
                        "startLine": 232,
                        "endLine": 232,
                        "startOffset": 6,
                        "endOffset": 17
                    }
                },
                {
                    "key": "AY5SlF0EAESW5py-ls1X",
                    "rule": "java:S2696",
                    "severity": "CRITICAL",
                    "component": "accumulo-4029:test/src/main/java/org/apache/accumulo/test/fate/zookeeper/FateIT.java",
                    "status": "OPEN",
                    "debt": "20min",
                    "type": "CODE_SMELL",
                    "textRange": {
                        "startLine": 233,
                        "endLine": 233,
                        "startOffset": 6,
                        "endOffset": 16
                    }
                },
                {
                    "key": "AY5SlF0EAESW5py-ls1H",
                    "rule": "java:S2293",
                    "severity": "MINOR",
                    "component": "accumulo-4029:test/src/main/java/org/apache/accumulo/test/fate/zookeeper/FateIT.java",
                    "status": "OPEN",
                    "debt": "1min",
                    "type": "CODE_SMELL",
                    "textRange": {
                        "startLine": 251,
                        "endLine": 251,
                        "startOffset": 51,
                        "endOffset": 60
                    }
                },
                {
                    "key": "AY5SlF0EAESW5py-ls1I",
                    "rule": "java:S2293",
                    "severity": "MINOR",
                    "component": "accumulo-4029:test/src/main/java/org/apache/accumulo/test/fate/zookeeper/FateIT.java",
                    "status": "OPEN",
                    "debt": "1min",
                    "type": "CODE_SMELL",
                    "textRange": {
                        "startLine": 253,
                        "endLine": 253,
                        "startOffset": 23,
                        "endOffset": 32
                    }
                },
                {
                    "key": "AY5SlF0EAESW5py-ls1J",
                    "rule": "java:S2293",
                    "severity": "MINOR",
                    "component": "accumulo-4029:test/src/main/java/org/apache/accumulo/test/fate/zookeeper/FateIT.java",
                    "status": "OPEN",
                    "debt": "1min",
                    "type": "CODE_SMELL",
                    "textRange": {
                        "startLine": 262,
                        "endLine": 262,
                        "startOffset": 33,
                        "endOffset": 42
                    }
                },
                {
                    "key": "AY5SlF0EAESW5py-ls1Y",
                    "rule": "java:S2696",
                    "severity": "CRITICAL",
                    "component": "accumulo-4029:test/src/main/java/org/apache/accumulo/test/fate/zookeeper/FateIT.java",
                    "status": "OPEN",
                    "debt": "20min",
                    "type": "CODE_SMELL",
                    "textRange": {
                        "startLine": 271,
                        "endLine": 271,
                        "startOffset": 4,
                        "endOffset": 15
                    }
                },
                {
                    "key": "AY5SlF0EAESW5py-ls1Z",
                    "rule": "java:S2696",
                    "severity": "CRITICAL",
                    "component": "accumulo-4029:test/src/main/java/org/apache/accumulo/test/fate/zookeeper/FateIT.java",
                    "status": "OPEN",
                    "debt": "20min",
                    "type": "CODE_SMELL",
                    "textRange": {
                        "startLine": 272,
                        "endLine": 272,
                        "startOffset": 4,
                        "endOffset": 14
                    }
                },
                {
                    "key": "AY5SlF0EAESW5py-ls1K",
                    "rule": "java:S2293",
                    "severity": "MINOR",
                    "component": "accumulo-4029:test/src/main/java/org/apache/accumulo/test/fate/zookeeper/FateIT.java",
                    "status": "OPEN",
                    "debt": "1min",
                    "type": "CODE_SMELL",
                    "textRange": {
                        "startLine": 284,
                        "endLine": 284,
                        "startOffset": 51,
                        "endOffset": 60
                    }
                },
                {
                    "key": "AY5SlF0EAESW5py-ls1L",
                    "rule": "java:S2293",
                    "severity": "MINOR",
                    "component": "accumulo-4029:test/src/main/java/org/apache/accumulo/test/fate/zookeeper/FateIT.java",
                    "status": "OPEN",
                    "debt": "1min",
                    "type": "CODE_SMELL",
                    "textRange": {
                        "startLine": 286,
                        "endLine": 286,
                        "startOffset": 23,
                        "endOffset": 32
                    }
                },
                {
                    "key": "AY5SlF0EAESW5py-ls1M",
                    "rule": "java:S2293",
                    "severity": "MINOR",
                    "component": "accumulo-4029:test/src/main/java/org/apache/accumulo/test/fate/zookeeper/FateIT.java",
                    "status": "OPEN",
                    "debt": "1min",
                    "type": "CODE_SMELL",
                    "textRange": {
                        "startLine": 295,
                        "endLine": 295,
                        "startOffset": 33,
                        "endOffset": 42
                    }
                },
                {
                    "key": "AY5SlF0EAESW5py-ls1a",
                    "rule": "java:S2696",
                    "severity": "CRITICAL",
                    "component": "accumulo-4029:test/src/main/java/org/apache/accumulo/test/fate/zookeeper/FateIT.java",
                    "status": "OPEN",
                    "debt": "20min",
                    "type": "CODE_SMELL",
                    "textRange": {
                        "startLine": 305,
                        "endLine": 305,
                        "startOffset": 6,
                        "endOffset": 17
                    }
                },
                {
                    "key": "AY5SlF0EAESW5py-ls1b",
                    "rule": "java:S2696",
                    "severity": "CRITICAL",
                    "component": "accumulo-4029:test/src/main/java/org/apache/accumulo/test/fate/zookeeper/FateIT.java",
                    "status": "OPEN",
                    "debt": "20min",
                    "type": "CODE_SMELL",
                    "textRange": {
                        "startLine": 306,
                        "endLine": 306,
                        "startOffset": 6,
                        "endOffset": 16
                    }
                },
                {
                    "key": "AY5SlF0EAESW5py-ls1N",
                    "rule": "java:S2293",
                    "severity": "MINOR",
                    "component": "accumulo-4029:test/src/main/java/org/apache/accumulo/test/fate/zookeeper/FateIT.java",
                    "status": "OPEN",
                    "debt": "1min",
                    "type": "CODE_SMELL",
                    "textRange": {
                        "startLine": 326,
                        "endLine": 326,
                        "startOffset": 51,
                        "endOffset": 60
                    }
                },
                {
                    "key": "AY5SlF0EAESW5py-ls1O",
                    "rule": "java:S2293",
                    "severity": "MINOR",
                    "component": "accumulo-4029:test/src/main/java/org/apache/accumulo/test/fate/zookeeper/FateIT.java",
                    "status": "OPEN",
                    "debt": "1min",
                    "type": "CODE_SMELL",
                    "textRange": {
                        "startLine": 328,
                        "endLine": 328,
                        "startOffset": 23,
                        "endOffset": 32
                    }
                },
                {
                    "key": "AY5SlF0EAESW5py-ls1P",
                    "rule": "java:S2293",
                    "severity": "MINOR",
                    "component": "accumulo-4029:test/src/main/java/org/apache/accumulo/test/fate/zookeeper/FateIT.java",
                    "status": "OPEN",
                    "debt": "1min",
                    "type": "CODE_SMELL",
                    "textRange": {
                        "startLine": 337,
                        "endLine": 337,
                        "startOffset": 33,
                        "endOffset": 42
                    }
                },
                {
                    "key": "AY5SlF0EAESW5py-ls1c",
                    "rule": "java:S2696",
                    "severity": "CRITICAL",
                    "component": "accumulo-4029:test/src/main/java/org/apache/accumulo/test/fate/zookeeper/FateIT.java",
                    "status": "OPEN",
                    "debt": "20min",
                    "type": "CODE_SMELL",
                    "textRange": {
                        "startLine": 347,
                        "endLine": 347,
                        "startOffset": 6,
                        "endOffset": 17
                    }
                },
                {
                    "key": "AY5SlF0EAESW5py-ls1d",
                    "rule": "java:S2696",
                    "severity": "CRITICAL",
                    "component": "accumulo-4029:test/src/main/java/org/apache/accumulo/test/fate/zookeeper/FateIT.java",
                    "status": "OPEN",
                    "debt": "20min",
                    "type": "CODE_SMELL",
                    "textRange": {
                        "startLine": 348,
                        "endLine": 348,
                        "startOffset": 6,
                        "endOffset": 16
                    }
                }
            ],
            "total": 31
        },
        "metrics": {
            "accumulo-4029:test/src/main/java/org/apache/accumulo/test/fate/zookeeper/FateIT.java": {
                "ncloc": "287",
                "complexity": "18"
            }
        }
    },
    {
        "commit_sha": "2c43f9188b85ca216d4e514ec10853855cd1a4e8",
        "issues": {
            "issues": [
                {
                    "key": "AY5SlF0EAESW5py-ls0_",
                    "rule": "java:S112",
                    "severity": "MAJOR",
                    "component": "accumulo-4029:test/src/main/java/org/apache/accumulo/test/fate/zookeeper/FateIT.java",
                    "status": "OPEN",
                    "debt": "20min",
                    "type": "CODE_SMELL",
                    "textRange": {
                        "startLine": 133,
                        "endLine": 133,
                        "startOffset": 36,
                        "endOffset": 45
                    }
                },
                {
                    "key": "AY5SlF0EAESW5py-ls1A",
                    "rule": "java:S112",
                    "severity": "MAJOR",
                    "component": "accumulo-4029:test/src/main/java/org/apache/accumulo/test/fate/zookeeper/FateIT.java",
                    "status": "OPEN",
                    "debt": "20min",
                    "type": "CODE_SMELL",
                    "textRange": {
                        "startLine": 144,
                        "endLine": 144,
                        "startOffset": 39,
                        "endOffset": 48
                    }
                },
                {
                    "key": "AY5SlF0EAESW5py-ls1B",
                    "rule": "java:S2293",
                    "severity": "MINOR",
                    "component": "accumulo-4029:test/src/main/java/org/apache/accumulo/test/fate/zookeeper/FateIT.java",
                    "status": "OPEN",
                    "debt": "1min",
                    "type": "CODE_SMELL",
                    "textRange": {
                        "startLine": 152,
                        "endLine": 152,
                        "startOffset": 51,
                        "endOffset": 60
                    }
                },
                {
                    "key": "AY5SlF0EAESW5py-ls1C",
                    "rule": "java:S2293",
                    "severity": "MINOR",
                    "component": "accumulo-4029:test/src/main/java/org/apache/accumulo/test/fate/zookeeper/FateIT.java",
                    "status": "OPEN",
                    "debt": "1min",
                    "type": "CODE_SMELL",
                    "textRange": {
                        "startLine": 154,
                        "endLine": 154,
                        "startOffset": 23,
                        "endOffset": 32
                    }
                },
                {
                    "key": "AY5SlF0EAESW5py-ls1D",
                    "rule": "java:S2293",
                    "severity": "MINOR",
                    "component": "accumulo-4029:test/src/main/java/org/apache/accumulo/test/fate/zookeeper/FateIT.java",
                    "status": "OPEN",
                    "debt": "1min",
                    "type": "CODE_SMELL",
                    "textRange": {
                        "startLine": 163,
                        "endLine": 163,
                        "startOffset": 33,
                        "endOffset": 42
                    }
                },
                {
                    "key": "AY5SlF0EAESW5py-ls1U",
                    "rule": "java:S2696",
                    "severity": "CRITICAL",
                    "component": "accumulo-4029:test/src/main/java/org/apache/accumulo/test/fate/zookeeper/FateIT.java",
                    "status": "OPEN",
                    "debt": "20min",
                    "type": "CODE_SMELL",
                    "textRange": {
                        "startLine": 173,
                        "endLine": 173,
                        "startOffset": 6,
                        "endOffset": 17
                    }
                },
                {
                    "key": "AY5SlF0EAESW5py-ls1V",
                    "rule": "java:S2696",
                    "severity": "CRITICAL",
                    "component": "accumulo-4029:test/src/main/java/org/apache/accumulo/test/fate/zookeeper/FateIT.java",
                    "status": "OPEN",
                    "debt": "20min",
                    "type": "CODE_SMELL",
                    "textRange": {
                        "startLine": 174,
                        "endLine": 174,
                        "startOffset": 6,
                        "endOffset": 16
                    }
                },
                {
                    "key": "AY5SlF0EAESW5py-ls1Q",
                    "rule": "java:S1192",
                    "severity": "CRITICAL",
                    "component": "accumulo-4029:test/src/main/java/org/apache/accumulo/test/fate/zookeeper/FateIT.java",
                    "status": "OPEN",
                    "debt": "12min",
                    "type": "CODE_SMELL",
                    "textRange": {
                        "startLine": 178,
                        "endLine": 178,
                        "startOffset": 84,
                        "endOffset": 93
                    }
                },
                {
                    "key": "AY5SlF0EAESW5py-ls1R",
                    "rule": "java:S1192",
                    "severity": "CRITICAL",
                    "component": "accumulo-4029:test/src/main/java/org/apache/accumulo/test/fate/zookeeper/FateIT.java",
                    "status": "OPEN",
                    "debt": "12min",
                    "type": "CODE_SMELL",
                    "textRange": {
                        "startLine": 178,
                        "endLine": 178,
                        "startOffset": 27,
                        "endOffset": 42
                    }
                },
                {
                    "key": "AY5SlF0EAESW5py-ls1S",
                    "rule": "java:S2189",
                    "severity": "BLOCKER",
                    "component": "accumulo-4029:test/src/main/java/org/apache/accumulo/test/fate/zookeeper/FateIT.java",
                    "status": "OPEN",
                    "debt": "15min",
                    "type": "BUG",
                    "textRange": {
                        "startLine": 193,
                        "endLine": 204,
                        "startOffset": 6,
                        "endOffset": 7
                    }
                },
                {
                    "key": "AY5SlF0EAESW5py-ls1T",
                    "rule": "java:S2589",
                    "severity": "MAJOR",
                    "component": "accumulo-4029:test/src/main/java/org/apache/accumulo/test/fate/zookeeper/FateIT.java",
                    "status": "OPEN",
                    "debt": "10min",
                    "type": "CODE_SMELL",
                    "textRange": {
                        "startLine": 193,
                        "endLine": 193,
                        "startOffset": 13,
                        "endOffset": 23
                    }
                },
                {
                    "key": "AY5SlF0EAESW5py-ls1E",
                    "rule": "java:S2293",
                    "severity": "MINOR",
                    "component": "accumulo-4029:test/src/main/java/org/apache/accumulo/test/fate/zookeeper/FateIT.java",
                    "status": "OPEN",
                    "debt": "1min",
                    "type": "CODE_SMELL",
                    "textRange": {
                        "startLine": 213,
                        "endLine": 213,
                        "startOffset": 51,
                        "endOffset": 60
                    }
                },
                {
                    "key": "AY5SlF0EAESW5py-ls1F",
                    "rule": "java:S2293",
                    "severity": "MINOR",
                    "component": "accumulo-4029:test/src/main/java/org/apache/accumulo/test/fate/zookeeper/FateIT.java",
                    "status": "OPEN",
                    "debt": "1min",
                    "type": "CODE_SMELL",
                    "textRange": {
                        "startLine": 215,
                        "endLine": 215,
                        "startOffset": 23,
                        "endOffset": 32
                    }
                },
                {
                    "key": "AY5SlF0EAESW5py-ls1G",
                    "rule": "java:S2293",
                    "severity": "MINOR",
                    "component": "accumulo-4029:test/src/main/java/org/apache/accumulo/test/fate/zookeeper/FateIT.java",
                    "status": "OPEN",
                    "debt": "1min",
                    "type": "CODE_SMELL",
                    "textRange": {
                        "startLine": 224,
                        "endLine": 224,
                        "startOffset": 33,
                        "endOffset": 42
                    }
                },
                {
                    "key": "AY5SlF0EAESW5py-ls1W",
                    "rule": "java:S2696",
                    "severity": "CRITICAL",
                    "component": "accumulo-4029:test/src/main/java/org/apache/accumulo/test/fate/zookeeper/FateIT.java",
                    "status": "OPEN",
                    "debt": "20min",
                    "type": "CODE_SMELL",
                    "textRange": {
                        "startLine": 234,
                        "endLine": 234,
                        "startOffset": 6,
                        "endOffset": 17
                    }
                },
                {
                    "key": "AY5SlF0EAESW5py-ls1X",
                    "rule": "java:S2696",
                    "severity": "CRITICAL",
                    "component": "accumulo-4029:test/src/main/java/org/apache/accumulo/test/fate/zookeeper/FateIT.java",
                    "status": "OPEN",
                    "debt": "20min",
                    "type": "CODE_SMELL",
                    "textRange": {
                        "startLine": 235,
                        "endLine": 235,
                        "startOffset": 6,
                        "endOffset": 16
                    }
                },
                {
                    "key": "AY5SlF0EAESW5py-ls1H",
                    "rule": "java:S2293",
                    "severity": "MINOR",
                    "component": "accumulo-4029:test/src/main/java/org/apache/accumulo/test/fate/zookeeper/FateIT.java",
                    "status": "OPEN",
                    "debt": "1min",
                    "type": "CODE_SMELL",
                    "textRange": {
                        "startLine": 256,
                        "endLine": 256,
                        "startOffset": 51,
                        "endOffset": 60
                    }
                },
                {
                    "key": "AY5SlF0EAESW5py-ls1I",
                    "rule": "java:S2293",
                    "severity": "MINOR",
                    "component": "accumulo-4029:test/src/main/java/org/apache/accumulo/test/fate/zookeeper/FateIT.java",
                    "status": "OPEN",
                    "debt": "1min",
                    "type": "CODE_SMELL",
                    "textRange": {
                        "startLine": 258,
                        "endLine": 258,
                        "startOffset": 23,
                        "endOffset": 32
                    }
                },
                {
                    "key": "AY5SlF0EAESW5py-ls1J",
                    "rule": "java:S2293",
                    "severity": "MINOR",
                    "component": "accumulo-4029:test/src/main/java/org/apache/accumulo/test/fate/zookeeper/FateIT.java",
                    "status": "OPEN",
                    "debt": "1min",
                    "type": "CODE_SMELL",
                    "textRange": {
                        "startLine": 267,
                        "endLine": 267,
                        "startOffset": 33,
                        "endOffset": 42
                    }
                },
                {
                    "key": "AY5SlF0EAESW5py-ls1Y",
                    "rule": "java:S2696",
                    "severity": "CRITICAL",
                    "component": "accumulo-4029:test/src/main/java/org/apache/accumulo/test/fate/zookeeper/FateIT.java",
                    "status": "OPEN",
                    "debt": "20min",
                    "type": "CODE_SMELL",
                    "textRange": {
                        "startLine": 276,
                        "endLine": 276,
                        "startOffset": 4,
                        "endOffset": 15
                    }
                },
                {
                    "key": "AY5SlF0EAESW5py-ls1Z",
                    "rule": "java:S2696",
                    "severity": "CRITICAL",
                    "component": "accumulo-4029:test/src/main/java/org/apache/accumulo/test/fate/zookeeper/FateIT.java",
                    "status": "OPEN",
                    "debt": "20min",
                    "type": "CODE_SMELL",
                    "textRange": {
                        "startLine": 277,
                        "endLine": 277,
                        "startOffset": 4,
                        "endOffset": 14
                    }
                },
                {
                    "key": "AY5SlF0EAESW5py-ls1K",
                    "rule": "java:S2293",
                    "severity": "MINOR",
                    "component": "accumulo-4029:test/src/main/java/org/apache/accumulo/test/fate/zookeeper/FateIT.java",
                    "status": "OPEN",
                    "debt": "1min",
                    "type": "CODE_SMELL",
                    "textRange": {
                        "startLine": 289,
                        "endLine": 289,
                        "startOffset": 51,
                        "endOffset": 60
                    }
                },
                {
                    "key": "AY5SlF0EAESW5py-ls1L",
                    "rule": "java:S2293",
                    "severity": "MINOR",
                    "component": "accumulo-4029:test/src/main/java/org/apache/accumulo/test/fate/zookeeper/FateIT.java",
                    "status": "OPEN",
                    "debt": "1min",
                    "type": "CODE_SMELL",
                    "textRange": {
                        "startLine": 291,
                        "endLine": 291,
                        "startOffset": 23,
                        "endOffset": 32
                    }
                },
                {
                    "key": "AY5SlF0EAESW5py-ls1M",
                    "rule": "java:S2293",
                    "severity": "MINOR",
                    "component": "accumulo-4029:test/src/main/java/org/apache/accumulo/test/fate/zookeeper/FateIT.java",
                    "status": "OPEN",
                    "debt": "1min",
                    "type": "CODE_SMELL",
                    "textRange": {
                        "startLine": 300,
                        "endLine": 300,
                        "startOffset": 33,
                        "endOffset": 42
                    }
                },
                {
                    "key": "AY5SlF0EAESW5py-ls1a",
                    "rule": "java:S2696",
                    "severity": "CRITICAL",
                    "component": "accumulo-4029:test/src/main/java/org/apache/accumulo/test/fate/zookeeper/FateIT.java",
                    "status": "OPEN",
                    "debt": "20min",
                    "type": "CODE_SMELL",
                    "textRange": {
                        "startLine": 310,
                        "endLine": 310,
                        "startOffset": 6,
                        "endOffset": 17
                    }
                },
                {
                    "key": "AY5SlF0EAESW5py-ls1b",
                    "rule": "java:S2696",
                    "severity": "CRITICAL",
                    "component": "accumulo-4029:test/src/main/java/org/apache/accumulo/test/fate/zookeeper/FateIT.java",
                    "status": "OPEN",
                    "debt": "20min",
                    "type": "CODE_SMELL",
                    "textRange": {
                        "startLine": 311,
                        "endLine": 311,
                        "startOffset": 6,
                        "endOffset": 16
                    }
                },
                {
                    "key": "AY5SlF0EAESW5py-ls1N",
                    "rule": "java:S2293",
                    "severity": "MINOR",
                    "component": "accumulo-4029:test/src/main/java/org/apache/accumulo/test/fate/zookeeper/FateIT.java",
                    "status": "OPEN",
                    "debt": "1min",
                    "type": "CODE_SMELL",
                    "textRange": {
                        "startLine": 333,
                        "endLine": 333,
                        "startOffset": 51,
                        "endOffset": 60
                    }
                },
                {
                    "key": "AY5SlF0EAESW5py-ls1O",
                    "rule": "java:S2293",
                    "severity": "MINOR",
                    "component": "accumulo-4029:test/src/main/java/org/apache/accumulo/test/fate/zookeeper/FateIT.java",
                    "status": "OPEN",
                    "debt": "1min",
                    "type": "CODE_SMELL",
                    "textRange": {
                        "startLine": 335,
                        "endLine": 335,
                        "startOffset": 23,
                        "endOffset": 32
                    }
                },
                {
                    "key": "AY5SlF0EAESW5py-ls1P",
                    "rule": "java:S2293",
                    "severity": "MINOR",
                    "component": "accumulo-4029:test/src/main/java/org/apache/accumulo/test/fate/zookeeper/FateIT.java",
                    "status": "OPEN",
                    "debt": "1min",
                    "type": "CODE_SMELL",
                    "textRange": {
                        "startLine": 344,
                        "endLine": 344,
                        "startOffset": 33,
                        "endOffset": 42
                    }
                },
                {
                    "key": "AY5SlF0EAESW5py-ls1c",
                    "rule": "java:S2696",
                    "severity": "CRITICAL",
                    "component": "accumulo-4029:test/src/main/java/org/apache/accumulo/test/fate/zookeeper/FateIT.java",
                    "status": "OPEN",
                    "debt": "20min",
                    "type": "CODE_SMELL",
                    "textRange": {
                        "startLine": 354,
                        "endLine": 354,
                        "startOffset": 6,
                        "endOffset": 17
                    }
                },
                {
                    "key": "AY5SlF0EAESW5py-ls1d",
                    "rule": "java:S2696",
                    "severity": "CRITICAL",
                    "component": "accumulo-4029:test/src/main/java/org/apache/accumulo/test/fate/zookeeper/FateIT.java",
                    "status": "OPEN",
                    "debt": "20min",
                    "type": "CODE_SMELL",
                    "textRange": {
                        "startLine": 355,
                        "endLine": 355,
                        "startOffset": 6,
                        "endOffset": 16
                    }
                }
            ],
            "total": 31
        },
        "metrics": {
            "accumulo-4029:test/src/main/java/org/apache/accumulo/test/fate/zookeeper/FateIT.java": {
                "ncloc": "293",
                "complexity": "22"
            }
        }
    }
]