[
    {
        "commit_sha": "9150d73e1dfa39690764875c05b90df5b1113549",
        "issues": {
            "issues": [
                {
                    "key": "AY5xu-r98f47XzIb7RJz",
                    "rule": "java:S120",
                    "severity": "MINOR",
                    "component": "accumulo-3339:server/manager/src/main/java/org/apache/accumulo/manager/tableOps/bulkVer2/PrepBulkImport.java",
                    "status": "OPEN",
                    "debt": "10min",
                    "type": "CODE_SMELL",
                    "textRange": {
                        "startLine": 19,
                        "endLine": 19,
                        "startOffset": 8,
                        "endOffset": 53
                    }
                },
                {
                    "key": "AY5xu-r98f47XzIb7RJ0",
                    "rule": "java:S3776",
                    "severity": "CRITICAL",
                    "component": "accumulo-3339:server/manager/src/main/java/org/apache/accumulo/manager/tableOps/bulkVer2/PrepBulkImport.java",
                    "status": "OPEN",
                    "debt": "16min",
                    "type": "CODE_SMELL",
                    "textRange": {
                        "startLine": 117,
                        "endLine": 117,
                        "startOffset": 14,
                        "endOffset": 36
                    }
                },
                {
                    "key": "AY5xu-r98f47XzIb7RJ1",
                    "rule": "java:S1130",
                    "severity": "MINOR",
                    "component": "accumulo-3339:server/manager/src/main/java/org/apache/accumulo/manager/tableOps/bulkVer2/PrepBulkImport.java",
                    "status": "OPEN",
                    "debt": "5min",
                    "type": "CODE_SMELL",
                    "textRange": {
                        "startLine": 118,
                        "endLine": 118,
                        "startOffset": 79,
                        "endOffset": 88
                    }
                },
                {
                    "key": "AY5xu-r98f47XzIb7RJx",
                    "rule": "java:S112",
                    "severity": "MAJOR",
                    "component": "accumulo-3339:server/manager/src/main/java/org/apache/accumulo/manager/tableOps/bulkVer2/PrepBulkImport.java",
                    "status": "OPEN",
                    "debt": "20min",
                    "type": "CODE_SMELL",
                    "textRange": {
                        "startLine": 118,
                        "endLine": 118,
                        "startOffset": 79,
                        "endOffset": 88
                    }
                },
                {
                    "key": "AY5xu-r98f47XzIb7RJy",
                    "rule": "java:S135",
                    "severity": "MINOR",
                    "component": "accumulo-3339:server/manager/src/main/java/org/apache/accumulo/manager/tableOps/bulkVer2/PrepBulkImport.java",
                    "status": "OPEN",
                    "debt": "20min",
                    "type": "CODE_SMELL",
                    "textRange": {
                        "startLine": 135,
                        "endLine": 135,
                        "startOffset": 4,
                        "endOffset": 9
                    }
                }
            ],
            "total": 5
        },
        "metrics": {
            "accumulo-3339:server/manager/src/main/java/org/apache/accumulo/manager/tableOps/bulkVer2/PrepBulkImport.java": {
                "ncloc": "184",
                "complexity": "35"
            }
        }
    },
    {
        "commit_sha": "3970a3e21506d1adb3003c5f0ecacfaaf1228611",
        "issues": {
            "issues": [
                {
                    "key": "AY5xu-r98f47XzIb7RJz",
                    "rule": "java:S120",
                    "severity": "MINOR",
                    "component": "accumulo-3339:server/manager/src/main/java/org/apache/accumulo/manager/tableOps/bulkVer2/PrepBulkImport.java",
                    "status": "OPEN",
                    "debt": "10min",
                    "type": "CODE_SMELL",
                    "textRange": {
                        "startLine": 19,
                        "endLine": 19,
                        "startOffset": 8,
                        "endOffset": 53
                    }
                },
                {
                    "key": "AY5xu-r98f47XzIb7RJ0",
                    "rule": "java:S3776",
                    "severity": "CRITICAL",
                    "component": "accumulo-3339:server/manager/src/main/java/org/apache/accumulo/manager/tableOps/bulkVer2/PrepBulkImport.java",
                    "status": "OPEN",
                    "debt": "16min",
                    "type": "CODE_SMELL",
                    "textRange": {
                        "startLine": 116,
                        "endLine": 116,
                        "startOffset": 14,
                        "endOffset": 36
                    }
                },
                {
                    "key": "AY5xu-r98f47XzIb7RJ1",
                    "rule": "java:S1130",
                    "severity": "MINOR",
                    "component": "accumulo-3339:server/manager/src/main/java/org/apache/accumulo/manager/tableOps/bulkVer2/PrepBulkImport.java",
                    "status": "OPEN",
                    "debt": "5min",
                    "type": "CODE_SMELL",
                    "textRange": {
                        "startLine": 117,
                        "endLine": 117,
                        "startOffset": 79,
                        "endOffset": 88
                    }
                },
                {
                    "key": "AY5xu-r98f47XzIb7RJx",
                    "rule": "java:S112",
                    "severity": "MAJOR",
                    "component": "accumulo-3339:server/manager/src/main/java/org/apache/accumulo/manager/tableOps/bulkVer2/PrepBulkImport.java",
                    "status": "OPEN",
                    "debt": "20min",
                    "type": "CODE_SMELL",
                    "textRange": {
                        "startLine": 117,
                        "endLine": 117,
                        "startOffset": 79,
                        "endOffset": 88
                    }
                },
                {
                    "key": "AY5xu-r98f47XzIb7RJy",
                    "rule": "java:S135",
                    "severity": "MINOR",
                    "component": "accumulo-3339:server/manager/src/main/java/org/apache/accumulo/manager/tableOps/bulkVer2/PrepBulkImport.java",
                    "status": "OPEN",
                    "debt": "20min",
                    "type": "CODE_SMELL",
                    "textRange": {
                        "startLine": 134,
                        "endLine": 134,
                        "startOffset": 4,
                        "endOffset": 9
                    }
                }
            ],
            "total": 5
        },
        "metrics": {
            "accumulo-3339:server/manager/src/main/java/org/apache/accumulo/manager/tableOps/bulkVer2/PrepBulkImport.java": {
                "ncloc": "183",
                "complexity": "35"
            }
        }
    }
]