[
    {
        "commit_sha": "75d0a0a850352743e584f78321cf7c51417f46f8",
        "issues": {
            "issues": [
                {
                    "key": "AY58F58e0GCajHYXYzoC",
                    "rule": "java:S3077",
                    "severity": "MINOR",
                    "component": "zookeeper-2093:zookeeper-server/src/test/java/org/apache/zookeeper/test/ACLTest.java",
                    "status": "OPEN",
                    "debt": "20min",
                    "type": "BUG",
                    "textRange": {
                        "startLine": 53,
                        "endLine": 53,
                        "startOffset": 12,
                        "endOffset": 35
                    }
                },
                {
                    "key": "AY58F58e0GCajHYXYzoA",
                    "rule": "java:S117",
                    "severity": "MINOR",
                    "component": "zookeeper-2093:zookeeper-server/src/test/java/org/apache/zookeeper/test/ACLTest.java",
                    "status": "OPEN",
                    "debt": "2min",
                    "type": "CODE_SMELL",
                    "textRange": {
                        "startLine": 67,
                        "endLine": 67,
                        "startOffset": 15,
                        "endOffset": 23
                    }
                },
                {
                    "key": "AY58F58e0GCajHYXYzoD",
                    "rule": "java:S1117",
                    "severity": "MAJOR",
                    "component": "zookeeper-2093:zookeeper-server/src/test/java/org/apache/zookeeper/test/ACLTest.java",
                    "status": "OPEN",
                    "debt": "5min",
                    "type": "CODE_SMELL",
                    "textRange": {
                        "startLine": 67,
                        "endLine": 67,
                        "startOffset": 15,
                        "endOffset": 23
                    }
                },
                {
                    "key": "AY58F58e0GCajHYXYzn7",
                    "rule": "java:S1192",
                    "severity": "CRITICAL",
                    "component": "zookeeper-2093:zookeeper-server/src/test/java/org/apache/zookeeper/test/ACLTest.java",
                    "status": "OPEN",
                    "debt": "8min",
                    "type": "CODE_SMELL",
                    "textRange": {
                        "startLine": 77,
                        "endLine": 77,
                        "startOffset": 21,
                        "endOffset": 66
                    }
                },
                {
                    "key": "AY58F58e0GCajHYXYzn8",
                    "rule": "java:S1192",
                    "severity": "CRITICAL",
                    "component": "zookeeper-2093:zookeeper-server/src/test/java/org/apache/zookeeper/test/ACLTest.java",
                    "status": "OPEN",
                    "debt": "8min",
                    "type": "CODE_SMELL",
                    "textRange": {
                        "startLine": 78,
                        "endLine": 78,
                        "startOffset": 81,
                        "endOffset": 110
                    }
                },
                {
                    "key": "AY58F58e0GCajHYXYzn9",
                    "rule": "java:S1192",
                    "severity": "CRITICAL",
                    "component": "zookeeper-2093:zookeeper-server/src/test/java/org/apache/zookeeper/test/ACLTest.java",
                    "status": "OPEN",
                    "debt": "14min",
                    "type": "CODE_SMELL",
                    "textRange": {
                        "startLine": 93,
                        "endLine": 93,
                        "startOffset": 83,
                        "endOffset": 108
                    }
                },
                {
                    "key": "AY58F58e0GCajHYXYzoE",
                    "rule": "java:S1075",
                    "severity": "MINOR",
                    "component": "zookeeper-2093:zookeeper-server/src/test/java/org/apache/zookeeper/test/ACLTest.java",
                    "status": "OPEN",
                    "debt": "20min",
                    "type": "CODE_SMELL",
                    "textRange": {
                        "startLine": 146,
                        "endLine": 146,
                        "startOffset": 23,
                        "endOffset": 26
                    }
                },
                {
                    "key": "AY58F58e0GCajHYXYzoF",
                    "rule": "java:S1481",
                    "severity": "MINOR",
                    "component": "zookeeper-2093:zookeeper-server/src/test/java/org/apache/zookeeper/test/ACLTest.java",
                    "status": "OPEN",
                    "debt": "5min",
                    "type": "CODE_SMELL",
                    "textRange": {
                        "startLine": 149,
                        "endLine": 149,
                        "startOffset": 16,
                        "endOffset": 20
                    }
                },
                {
                    "key": "AY58F58e0GCajHYXYzoG",
                    "rule": "java:S1075",
                    "severity": "MINOR",
                    "component": "zookeeper-2093:zookeeper-server/src/test/java/org/apache/zookeeper/test/ACLTest.java",
                    "status": "OPEN",
                    "debt": "20min",
                    "type": "CODE_SMELL",
                    "textRange": {
                        "startLine": 152,
                        "endLine": 152,
                        "startOffset": 23,
                        "endOffset": 26
                    }
                },
                {
                    "key": "AY58F58e0GCajHYXYzoH",
                    "rule": "java:S1075",
                    "severity": "MINOR",
                    "component": "zookeeper-2093:zookeeper-server/src/test/java/org/apache/zookeeper/test/ACLTest.java",
                    "status": "OPEN",
                    "debt": "20min",
                    "type": "CODE_SMELL",
                    "textRange": {
                        "startLine": 180,
                        "endLine": 180,
                        "startOffset": 23,
                        "endOffset": 26
                    }
                },
                {
                    "key": "AY58F58e0GCajHYXYzn_",
                    "rule": "java:S1192",
                    "severity": "CRITICAL",
                    "component": "zookeeper-2093:zookeeper-server/src/test/java/org/apache/zookeeper/test/ACLTest.java",
                    "status": "OPEN",
                    "debt": "8min",
                    "type": "CODE_SMELL",
                    "textRange": {
                        "startLine": 232,
                        "endLine": 232,
                        "startOffset": 21,
                        "endOffset": 74
                    }
                },
                {
                    "key": "AY58F58e0GCajHYXYzn-",
                    "rule": "java:S1192",
                    "severity": "CRITICAL",
                    "component": "zookeeper-2093:zookeeper-server/src/test/java/org/apache/zookeeper/test/ACLTest.java",
                    "status": "OPEN",
                    "debt": "8min",
                    "type": "CODE_SMELL",
                    "textRange": {
                        "startLine": 277,
                        "endLine": 277,
                        "startOffset": 21,
                        "endOffset": 78
                    }
                },
                {
                    "key": "AY58F6CT0GCajHYXY0Ix",
                    "rule": "java:S1066",
                    "severity": "MAJOR",
                    "component": "zookeeper-2093:zookeeper-server/src/main/java/org/apache/zookeeper/server/FinalRequestProcessor.java",
                    "status": "OPEN",
                    "debt": "5min",
                    "type": "CODE_SMELL",
                    "textRange": {
                        "startLine": 123,
                        "endLine": 123,
                        "startOffset": 12,
                        "endOffset": 14
                    }
                },
                {
                    "key": "AY58F6CT0GCajHYXY0I0",
                    "rule": "java:S3776",
                    "severity": "CRITICAL",
                    "component": "zookeeper-2093:zookeeper-server/src/main/java/org/apache/zookeeper/server/FinalRequestProcessor.java",
                    "status": "OPEN",
                    "debt": "1h10min",
                    "type": "CODE_SMELL",
                    "textRange": {
                        "startLine": 147,
                        "endLine": 147,
                        "startOffset": 16,
                        "endOffset": 30
                    }
                },
                {
                    "key": "AY58F6CT0GCajHYXY0I1",
                    "rule": "java:S131",
                    "severity": "CRITICAL",
                    "component": "zookeeper-2093:zookeeper-server/src/main/java/org/apache/zookeeper/server/FinalRequestProcessor.java",
                    "status": "OPEN",
                    "debt": "5min",
                    "type": "CODE_SMELL",
                    "textRange": {
                        "startLine": 214,
                        "endLine": 214,
                        "startOffset": 12,
                        "endOffset": 18
                    }
                },
                {
                    "key": "AY58F6CT0GCajHYXY0Iw",
                    "rule": "java:S1192",
                    "severity": "CRITICAL",
                    "component": "zookeeper-2093:zookeeper-server/src/main/java/org/apache/zookeeper/server/FinalRequestProcessor.java",
                    "status": "OPEN",
                    "debt": "12min",
                    "type": "CODE_SMELL",
                    "textRange": {
                        "startLine": 219,
                        "endLine": 219,
                        "startOffset": 106,
                        "endOffset": 116
                    }
                },
                {
                    "key": "AY58F6CT0GCajHYXY0Iy",
                    "rule": "java:S1141",
                    "severity": "MAJOR",
                    "component": "zookeeper-2093:zookeeper-server/src/main/java/org/apache/zookeeper/server/FinalRequestProcessor.java",
                    "status": "OPEN",
                    "debt": "20min",
                    "type": "CODE_SMELL",
                    "textRange": {
                        "startLine": 277,
                        "endLine": 277,
                        "startOffset": 20,
                        "endOffset": 23
                    }
                },
                {
                    "key": "AY58F6CT0GCajHYXY0I2",
                    "rule": "java:S1135",
                    "severity": "INFO",
                    "component": "zookeeper-2093:zookeeper-server/src/main/java/org/apache/zookeeper/server/FinalRequestProcessor.java",
                    "status": "OPEN",
                    "debt": "0min",
                    "type": "CODE_SMELL",
                    "textRange": {
                        "startLine": 366,
                        "endLine": 366,
                        "startOffset": 0,
                        "endOffset": 80
                    }
                },
                {
                    "key": "AY58F6CT0GCajHYXY0Iz",
                    "rule": "java:S1141",
                    "severity": "MAJOR",
                    "component": "zookeeper-2093:zookeeper-server/src/main/java/org/apache/zookeeper/server/FinalRequestProcessor.java",
                    "status": "OPEN",
                    "debt": "20min",
                    "type": "CODE_SMELL",
                    "textRange": {
                        "startLine": 438,
                        "endLine": 438,
                        "startOffset": 16,
                        "endOffset": 19
                    }
                },
                {
                    "key": "AY58F6CT0GCajHYXY0I3",
                    "rule": "java:S1130",
                    "severity": "MINOR",
                    "component": "zookeeper-2093:zookeeper-server/src/main/java/org/apache/zookeeper/server/FinalRequestProcessor.java",
                    "status": "OPEN",
                    "debt": "5min",
                    "type": "CODE_SMELL",
                    "textRange": {
                        "startLine": 623,
                        "endLine": 623,
                        "startOffset": 120,
                        "endOffset": 131
                    }
                },
                {
                    "key": "AY58F6CT0GCajHYXY0I4",
                    "rule": "java:S1130",
                    "severity": "MINOR",
                    "component": "zookeeper-2093:zookeeper-server/src/main/java/org/apache/zookeeper/server/FinalRequestProcessor.java",
                    "status": "OPEN",
                    "debt": "5min",
                    "type": "CODE_SMELL",
                    "textRange": {
                        "startLine": 636,
                        "endLine": 636,
                        "startOffset": 116,
                        "endOffset": 127
                    }
                }
            ],
            "total": 21
        },
        "metrics": {
            "zookeeper-2093:zookeeper-server/src/test/java/org/apache/zookeeper/test/ACLTest.java": {
                "ncloc": "243",
                "complexity": "16"
            },
            "zookeeper-2093:zookeeper-server/src/main/java/org/apache/zookeeper/server/FinalRequestProcessor.java": {
                "ncloc": "579",
                "complexity": "100"
            }
        }
    },
    {
        "commit_sha": "11448c2b4adf786c66582d5b2235c85ab51641db",
        "issues": {
            "issues": [
                {
                    "key": "AY58GR7x0GCajHYXY-IP",
                    "rule": "java:S1075",
                    "severity": "MINOR",
                    "component": "zookeeper-2093:zookeeper-server/src/test/java/org/apache/zookeeper/test/ACLTest.java",
                    "status": "OPEN",
                    "debt": "20min",
                    "type": "CODE_SMELL",
                    "textRange": {
                        "startLine": 319,
                        "endLine": 319,
                        "startOffset": 22,
                        "endOffset": 42
                    }
                },
                {
                    "key": "AY58F58e0GCajHYXYzoC",
                    "rule": "java:S3077",
                    "severity": "MINOR",
                    "component": "zookeeper-2093:zookeeper-server/src/test/java/org/apache/zookeeper/test/ACLTest.java",
                    "status": "OPEN",
                    "debt": "20min",
                    "type": "BUG",
                    "textRange": {
                        "startLine": 59,
                        "endLine": 59,
                        "startOffset": 12,
                        "endOffset": 35
                    }
                },
                {
                    "key": "AY58F58e0GCajHYXYzoA",
                    "rule": "java:S117",
                    "severity": "MINOR",
                    "component": "zookeeper-2093:zookeeper-server/src/test/java/org/apache/zookeeper/test/ACLTest.java",
                    "status": "OPEN",
                    "debt": "2min",
                    "type": "CODE_SMELL",
                    "textRange": {
                        "startLine": 73,
                        "endLine": 73,
                        "startOffset": 15,
                        "endOffset": 23
                    }
                },
                {
                    "key": "AY58F58e0GCajHYXYzoD",
                    "rule": "java:S1117",
                    "severity": "MAJOR",
                    "component": "zookeeper-2093:zookeeper-server/src/test/java/org/apache/zookeeper/test/ACLTest.java",
                    "status": "OPEN",
                    "debt": "5min",
                    "type": "CODE_SMELL",
                    "textRange": {
                        "startLine": 73,
                        "endLine": 73,
                        "startOffset": 15,
                        "endOffset": 23
                    }
                },
                {
                    "key": "AY58F58e0GCajHYXYzn7",
                    "rule": "java:S1192",
                    "severity": "CRITICAL",
                    "component": "zookeeper-2093:zookeeper-server/src/test/java/org/apache/zookeeper/test/ACLTest.java",
                    "status": "OPEN",
                    "debt": "12min",
                    "type": "CODE_SMELL",
                    "textRange": {
                        "startLine": 83,
                        "endLine": 83,
                        "startOffset": 21,
                        "endOffset": 66
                    }
                },
                {
                    "key": "AY58F58e0GCajHYXYzn8",
                    "rule": "java:S1192",
                    "severity": "CRITICAL",
                    "component": "zookeeper-2093:zookeeper-server/src/test/java/org/apache/zookeeper/test/ACLTest.java",
                    "status": "OPEN",
                    "debt": "12min",
                    "type": "CODE_SMELL",
                    "textRange": {
                        "startLine": 84,
                        "endLine": 84,
                        "startOffset": 81,
                        "endOffset": 110
                    }
                },
                {
                    "key": "AY58F58e0GCajHYXYzn9",
                    "rule": "java:S1192",
                    "severity": "CRITICAL",
                    "component": "zookeeper-2093:zookeeper-server/src/test/java/org/apache/zookeeper/test/ACLTest.java",
                    "status": "OPEN",
                    "debt": "18min",
                    "type": "CODE_SMELL",
                    "textRange": {
                        "startLine": 99,
                        "endLine": 99,
                        "startOffset": 83,
                        "endOffset": 108
                    }
                },
                {
                    "key": "AY58F58e0GCajHYXYzoE",
                    "rule": "java:S1075",
                    "severity": "MINOR",
                    "component": "zookeeper-2093:zookeeper-server/src/test/java/org/apache/zookeeper/test/ACLTest.java",
                    "status": "OPEN",
                    "debt": "20min",
                    "type": "CODE_SMELL",
                    "textRange": {
                        "startLine": 152,
                        "endLine": 152,
                        "startOffset": 23,
                        "endOffset": 26
                    }
                },
                {
                    "key": "AY58F58e0GCajHYXYzoF",
                    "rule": "java:S1481",
                    "severity": "MINOR",
                    "component": "zookeeper-2093:zookeeper-server/src/test/java/org/apache/zookeeper/test/ACLTest.java",
                    "status": "OPEN",
                    "debt": "5min",
                    "type": "CODE_SMELL",
                    "textRange": {
                        "startLine": 155,
                        "endLine": 155,
                        "startOffset": 16,
                        "endOffset": 20
                    }
                },
                {
                    "key": "AY58F58e0GCajHYXYzoG",
                    "rule": "java:S1075",
                    "severity": "MINOR",
                    "component": "zookeeper-2093:zookeeper-server/src/test/java/org/apache/zookeeper/test/ACLTest.java",
                    "status": "OPEN",
                    "debt": "20min",
                    "type": "CODE_SMELL",
                    "textRange": {
                        "startLine": 158,
                        "endLine": 158,
                        "startOffset": 23,
                        "endOffset": 26
                    }
                },
                {
                    "key": "AY58F58e0GCajHYXYzoH",
                    "rule": "java:S1075",
                    "severity": "MINOR",
                    "component": "zookeeper-2093:zookeeper-server/src/test/java/org/apache/zookeeper/test/ACLTest.java",
                    "status": "OPEN",
                    "debt": "20min",
                    "type": "CODE_SMELL",
                    "textRange": {
                        "startLine": 186,
                        "endLine": 186,
                        "startOffset": 23,
                        "endOffset": 26
                    }
                },
                {
                    "key": "AY58F58e0GCajHYXYzn_",
                    "rule": "java:S1192",
                    "severity": "CRITICAL",
                    "component": "zookeeper-2093:zookeeper-server/src/test/java/org/apache/zookeeper/test/ACLTest.java",
                    "status": "OPEN",
                    "debt": "8min",
                    "type": "CODE_SMELL",
                    "textRange": {
                        "startLine": 238,
                        "endLine": 238,
                        "startOffset": 21,
                        "endOffset": 74
                    }
                },
                {
                    "key": "AY58F58e0GCajHYXYzn-",
                    "rule": "java:S1192",
                    "severity": "CRITICAL",
                    "component": "zookeeper-2093:zookeeper-server/src/test/java/org/apache/zookeeper/test/ACLTest.java",
                    "status": "OPEN",
                    "debt": "8min",
                    "type": "CODE_SMELL",
                    "textRange": {
                        "startLine": 283,
                        "endLine": 283,
                        "startOffset": 21,
                        "endOffset": 78
                    }
                },
                {
                    "key": "AY58F6CT0GCajHYXY0I2",
                    "rule": "java:S1135",
                    "severity": "INFO",
                    "component": "zookeeper-2093:zookeeper-server/src/main/java/org/apache/zookeeper/server/FinalRequestProcessor.java",
                    "status": "CLOSED",
                    "debt": "0min",
                    "type": "CODE_SMELL",
                    "textRange": {
                        "startLine": 366,
                        "endLine": 366,
                        "startOffset": 0,
                        "endOffset": 80
                    }
                },
                {
                    "key": "AY58F6CT0GCajHYXY0Ix",
                    "rule": "java:S1066",
                    "severity": "MAJOR",
                    "component": "zookeeper-2093:zookeeper-server/src/main/java/org/apache/zookeeper/server/FinalRequestProcessor.java",
                    "status": "OPEN",
                    "debt": "5min",
                    "type": "CODE_SMELL",
                    "textRange": {
                        "startLine": 123,
                        "endLine": 123,
                        "startOffset": 12,
                        "endOffset": 14
                    }
                },
                {
                    "key": "AY58F6CT0GCajHYXY0I0",
                    "rule": "java:S3776",
                    "severity": "CRITICAL",
                    "component": "zookeeper-2093:zookeeper-server/src/main/java/org/apache/zookeeper/server/FinalRequestProcessor.java",
                    "status": "OPEN",
                    "debt": "1h12min",
                    "type": "CODE_SMELL",
                    "textRange": {
                        "startLine": 147,
                        "endLine": 147,
                        "startOffset": 16,
                        "endOffset": 30
                    }
                },
                {
                    "key": "AY58F6CT0GCajHYXY0I1",
                    "rule": "java:S131",
                    "severity": "CRITICAL",
                    "component": "zookeeper-2093:zookeeper-server/src/main/java/org/apache/zookeeper/server/FinalRequestProcessor.java",
                    "status": "OPEN",
                    "debt": "5min",
                    "type": "CODE_SMELL",
                    "textRange": {
                        "startLine": 214,
                        "endLine": 214,
                        "startOffset": 12,
                        "endOffset": 18
                    }
                },
                {
                    "key": "AY58F6CT0GCajHYXY0Iw",
                    "rule": "java:S1192",
                    "severity": "CRITICAL",
                    "component": "zookeeper-2093:zookeeper-server/src/main/java/org/apache/zookeeper/server/FinalRequestProcessor.java",
                    "status": "OPEN",
                    "debt": "12min",
                    "type": "CODE_SMELL",
                    "textRange": {
                        "startLine": 219,
                        "endLine": 219,
                        "startOffset": 106,
                        "endOffset": 116
                    }
                },
                {
                    "key": "AY58F6CT0GCajHYXY0Iy",
                    "rule": "java:S1141",
                    "severity": "MAJOR",
                    "component": "zookeeper-2093:zookeeper-server/src/main/java/org/apache/zookeeper/server/FinalRequestProcessor.java",
                    "status": "OPEN",
                    "debt": "20min",
                    "type": "CODE_SMELL",
                    "textRange": {
                        "startLine": 277,
                        "endLine": 277,
                        "startOffset": 20,
                        "endOffset": 23
                    }
                },
                {
                    "key": "AY58F6CT0GCajHYXY0Iz",
                    "rule": "java:S1141",
                    "severity": "MAJOR",
                    "component": "zookeeper-2093:zookeeper-server/src/main/java/org/apache/zookeeper/server/FinalRequestProcessor.java",
                    "status": "OPEN",
                    "debt": "20min",
                    "type": "CODE_SMELL",
                    "textRange": {
                        "startLine": 448,
                        "endLine": 448,
                        "startOffset": 16,
                        "endOffset": 19
                    }
                },
                {
                    "key": "AY58F6CT0GCajHYXY0I3",
                    "rule": "java:S1130",
                    "severity": "MINOR",
                    "component": "zookeeper-2093:zookeeper-server/src/main/java/org/apache/zookeeper/server/FinalRequestProcessor.java",
                    "status": "OPEN",
                    "debt": "5min",
                    "type": "CODE_SMELL",
                    "textRange": {
                        "startLine": 633,
                        "endLine": 633,
                        "startOffset": 120,
                        "endOffset": 131
                    }
                },
                {
                    "key": "AY58F6CT0GCajHYXY0I4",
                    "rule": "java:S1130",
                    "severity": "MINOR",
                    "component": "zookeeper-2093:zookeeper-server/src/main/java/org/apache/zookeeper/server/FinalRequestProcessor.java",
                    "status": "OPEN",
                    "debt": "5min",
                    "type": "CODE_SMELL",
                    "textRange": {
                        "startLine": 646,
                        "endLine": 646,
                        "startOffset": 116,
                        "endOffset": 127
                    }
                }
            ],
            "total": 22
        },
        "metrics": {
            "zookeeper-2093:zookeeper-server/src/test/java/org/apache/zookeeper/test/ACLTest.java": {
                "ncloc": "330",
                "complexity": "18"
            },
            "zookeeper-2093:zookeeper-server/src/main/java/org/apache/zookeeper/server/FinalRequestProcessor.java": {
                "ncloc": "590",
                "complexity": "101"
            }
        }
    },
    {
        "commit_sha": "7e83e4f6cef02bee448132c2f9c8ec1080a4abfb",
        "issues": {
            "issues": [
                {
                    "key": "AY58GR7x0GCajHYXY-IP",
                    "rule": "java:S1075",
                    "severity": "MINOR",
                    "component": "zookeeper-2093:zookeeper-server/src/test/java/org/apache/zookeeper/test/ACLTest.java",
                    "status": "OPEN",
                    "debt": "20min",
                    "type": "CODE_SMELL",
                    "textRange": {
                        "startLine": 319,
                        "endLine": 319,
                        "startOffset": 22,
                        "endOffset": 42
                    }
                },
                {
                    "key": "AY58F58e0GCajHYXYzoC",
                    "rule": "java:S3077",
                    "severity": "MINOR",
                    "component": "zookeeper-2093:zookeeper-server/src/test/java/org/apache/zookeeper/test/ACLTest.java",
                    "status": "OPEN",
                    "debt": "20min",
                    "type": "BUG",
                    "textRange": {
                        "startLine": 59,
                        "endLine": 59,
                        "startOffset": 12,
                        "endOffset": 35
                    }
                },
                {
                    "key": "AY58F58e0GCajHYXYzoA",
                    "rule": "java:S117",
                    "severity": "MINOR",
                    "component": "zookeeper-2093:zookeeper-server/src/test/java/org/apache/zookeeper/test/ACLTest.java",
                    "status": "OPEN",
                    "debt": "2min",
                    "type": "CODE_SMELL",
                    "textRange": {
                        "startLine": 73,
                        "endLine": 73,
                        "startOffset": 15,
                        "endOffset": 23
                    }
                },
                {
                    "key": "AY58F58e0GCajHYXYzoD",
                    "rule": "java:S1117",
                    "severity": "MAJOR",
                    "component": "zookeeper-2093:zookeeper-server/src/test/java/org/apache/zookeeper/test/ACLTest.java",
                    "status": "OPEN",
                    "debt": "5min",
                    "type": "CODE_SMELL",
                    "textRange": {
                        "startLine": 73,
                        "endLine": 73,
                        "startOffset": 15,
                        "endOffset": 23
                    }
                },
                {
                    "key": "AY58F58e0GCajHYXYzn7",
                    "rule": "java:S1192",
                    "severity": "CRITICAL",
                    "component": "zookeeper-2093:zookeeper-server/src/test/java/org/apache/zookeeper/test/ACLTest.java",
                    "status": "OPEN",
                    "debt": "12min",
                    "type": "CODE_SMELL",
                    "textRange": {
                        "startLine": 83,
                        "endLine": 83,
                        "startOffset": 21,
                        "endOffset": 66
                    }
                },
                {
                    "key": "AY58F58e0GCajHYXYzn8",
                    "rule": "java:S1192",
                    "severity": "CRITICAL",
                    "component": "zookeeper-2093:zookeeper-server/src/test/java/org/apache/zookeeper/test/ACLTest.java",
                    "status": "OPEN",
                    "debt": "12min",
                    "type": "CODE_SMELL",
                    "textRange": {
                        "startLine": 84,
                        "endLine": 84,
                        "startOffset": 81,
                        "endOffset": 110
                    }
                },
                {
                    "key": "AY58F58e0GCajHYXYzn9",
                    "rule": "java:S1192",
                    "severity": "CRITICAL",
                    "component": "zookeeper-2093:zookeeper-server/src/test/java/org/apache/zookeeper/test/ACLTest.java",
                    "status": "OPEN",
                    "debt": "18min",
                    "type": "CODE_SMELL",
                    "textRange": {
                        "startLine": 99,
                        "endLine": 99,
                        "startOffset": 83,
                        "endOffset": 108
                    }
                },
                {
                    "key": "AY58F58e0GCajHYXYzoE",
                    "rule": "java:S1075",
                    "severity": "MINOR",
                    "component": "zookeeper-2093:zookeeper-server/src/test/java/org/apache/zookeeper/test/ACLTest.java",
                    "status": "OPEN",
                    "debt": "20min",
                    "type": "CODE_SMELL",
                    "textRange": {
                        "startLine": 152,
                        "endLine": 152,
                        "startOffset": 23,
                        "endOffset": 26
                    }
                },
                {
                    "key": "AY58F58e0GCajHYXYzoF",
                    "rule": "java:S1481",
                    "severity": "MINOR",
                    "component": "zookeeper-2093:zookeeper-server/src/test/java/org/apache/zookeeper/test/ACLTest.java",
                    "status": "OPEN",
                    "debt": "5min",
                    "type": "CODE_SMELL",
                    "textRange": {
                        "startLine": 155,
                        "endLine": 155,
                        "startOffset": 16,
                        "endOffset": 20
                    }
                },
                {
                    "key": "AY58F58e0GCajHYXYzoG",
                    "rule": "java:S1075",
                    "severity": "MINOR",
                    "component": "zookeeper-2093:zookeeper-server/src/test/java/org/apache/zookeeper/test/ACLTest.java",
                    "status": "OPEN",
                    "debt": "20min",
                    "type": "CODE_SMELL",
                    "textRange": {
                        "startLine": 158,
                        "endLine": 158,
                        "startOffset": 23,
                        "endOffset": 26
                    }
                },
                {
                    "key": "AY58F58e0GCajHYXYzoH",
                    "rule": "java:S1075",
                    "severity": "MINOR",
                    "component": "zookeeper-2093:zookeeper-server/src/test/java/org/apache/zookeeper/test/ACLTest.java",
                    "status": "OPEN",
                    "debt": "20min",
                    "type": "CODE_SMELL",
                    "textRange": {
                        "startLine": 186,
                        "endLine": 186,
                        "startOffset": 23,
                        "endOffset": 26
                    }
                },
                {
                    "key": "AY58F58e0GCajHYXYzn_",
                    "rule": "java:S1192",
                    "severity": "CRITICAL",
                    "component": "zookeeper-2093:zookeeper-server/src/test/java/org/apache/zookeeper/test/ACLTest.java",
                    "status": "OPEN",
                    "debt": "8min",
                    "type": "CODE_SMELL",
                    "textRange": {
                        "startLine": 238,
                        "endLine": 238,
                        "startOffset": 21,
                        "endOffset": 74
                    }
                },
                {
                    "key": "AY58F58e0GCajHYXYzn-",
                    "rule": "java:S1192",
                    "severity": "CRITICAL",
                    "component": "zookeeper-2093:zookeeper-server/src/test/java/org/apache/zookeeper/test/ACLTest.java",
                    "status": "OPEN",
                    "debt": "8min",
                    "type": "CODE_SMELL",
                    "textRange": {
                        "startLine": 283,
                        "endLine": 283,
                        "startOffset": 21,
                        "endOffset": 78
                    }
                },
                {
                    "key": "AY58F6CT0GCajHYXY0I2",
                    "rule": "java:S1135",
                    "severity": "INFO",
                    "component": "zookeeper-2093:zookeeper-server/src/main/java/org/apache/zookeeper/server/FinalRequestProcessor.java",
                    "status": "CLOSED",
                    "debt": "0min",
                    "type": "CODE_SMELL",
                    "textRange": {
                        "startLine": 366,
                        "endLine": 366,
                        "startOffset": 0,
                        "endOffset": 80
                    }
                },
                {
                    "key": "AY58F6CT0GCajHYXY0Ix",
                    "rule": "java:S1066",
                    "severity": "MAJOR",
                    "component": "zookeeper-2093:zookeeper-server/src/main/java/org/apache/zookeeper/server/FinalRequestProcessor.java",
                    "status": "OPEN",
                    "debt": "5min",
                    "type": "CODE_SMELL",
                    "textRange": {
                        "startLine": 123,
                        "endLine": 123,
                        "startOffset": 12,
                        "endOffset": 14
                    }
                },
                {
                    "key": "AY58F6CT0GCajHYXY0I0",
                    "rule": "java:S3776",
                    "severity": "CRITICAL",
                    "component": "zookeeper-2093:zookeeper-server/src/main/java/org/apache/zookeeper/server/FinalRequestProcessor.java",
                    "status": "OPEN",
                    "debt": "1h12min",
                    "type": "CODE_SMELL",
                    "textRange": {
                        "startLine": 147,
                        "endLine": 147,
                        "startOffset": 16,
                        "endOffset": 30
                    }
                },
                {
                    "key": "AY58F6CT0GCajHYXY0I1",
                    "rule": "java:S131",
                    "severity": "CRITICAL",
                    "component": "zookeeper-2093:zookeeper-server/src/main/java/org/apache/zookeeper/server/FinalRequestProcessor.java",
                    "status": "OPEN",
                    "debt": "5min",
                    "type": "CODE_SMELL",
                    "textRange": {
                        "startLine": 214,
                        "endLine": 214,
                        "startOffset": 12,
                        "endOffset": 18
                    }
                },
                {
                    "key": "AY58F6CT0GCajHYXY0Iw",
                    "rule": "java:S1192",
                    "severity": "CRITICAL",
                    "component": "zookeeper-2093:zookeeper-server/src/main/java/org/apache/zookeeper/server/FinalRequestProcessor.java",
                    "status": "OPEN",
                    "debt": "12min",
                    "type": "CODE_SMELL",
                    "textRange": {
                        "startLine": 219,
                        "endLine": 219,
                        "startOffset": 106,
                        "endOffset": 116
                    }
                },
                {
                    "key": "AY58F6CT0GCajHYXY0Iy",
                    "rule": "java:S1141",
                    "severity": "MAJOR",
                    "component": "zookeeper-2093:zookeeper-server/src/main/java/org/apache/zookeeper/server/FinalRequestProcessor.java",
                    "status": "OPEN",
                    "debt": "20min",
                    "type": "CODE_SMELL",
                    "textRange": {
                        "startLine": 277,
                        "endLine": 277,
                        "startOffset": 20,
                        "endOffset": 23
                    }
                },
                {
                    "key": "AY58F6CT0GCajHYXY0Iz",
                    "rule": "java:S1141",
                    "severity": "MAJOR",
                    "component": "zookeeper-2093:zookeeper-server/src/main/java/org/apache/zookeeper/server/FinalRequestProcessor.java",
                    "status": "OPEN",
                    "debt": "20min",
                    "type": "CODE_SMELL",
                    "textRange": {
                        "startLine": 447,
                        "endLine": 447,
                        "startOffset": 16,
                        "endOffset": 19
                    }
                },
                {
                    "key": "AY58F6CT0GCajHYXY0I3",
                    "rule": "java:S1130",
                    "severity": "MINOR",
                    "component": "zookeeper-2093:zookeeper-server/src/main/java/org/apache/zookeeper/server/FinalRequestProcessor.java",
                    "status": "OPEN",
                    "debt": "5min",
                    "type": "CODE_SMELL",
                    "textRange": {
                        "startLine": 632,
                        "endLine": 632,
                        "startOffset": 120,
                        "endOffset": 131
                    }
                },
                {
                    "key": "AY58F6CT0GCajHYXY0I4",
                    "rule": "java:S1130",
                    "severity": "MINOR",
                    "component": "zookeeper-2093:zookeeper-server/src/main/java/org/apache/zookeeper/server/FinalRequestProcessor.java",
                    "status": "OPEN",
                    "debt": "5min",
                    "type": "CODE_SMELL",
                    "textRange": {
                        "startLine": 645,
                        "endLine": 645,
                        "startOffset": 116,
                        "endOffset": 127
                    }
                }
            ],
            "total": 22
        },
        "metrics": {
            "zookeeper-2093:zookeeper-server/src/test/java/org/apache/zookeeper/test/ACLTest.java": {
                "ncloc": "330",
                "complexity": "18"
            },
            "zookeeper-2093:zookeeper-server/src/main/java/org/apache/zookeeper/server/FinalRequestProcessor.java": {
                "ncloc": "589",
                "complexity": "101"
            }
        }
    }
]